odoo10_addon_stock_ownership_availability_rules-10.0.1.0.2-py2.7-nspkg.pth
odoo/addons/stock_ownership_availability_rules/README.rst
odoo/addons/stock_ownership_availability_rules/__init__.py
odoo/addons/stock_ownership_availability_rules/__manifest__.py
odoo/addons/stock_ownership_availability_rules/i18n/es.po
odoo/addons/stock_ownership_availability_rules/i18n/fr.po
odoo/addons/stock_ownership_availability_rules/i18n/hr.po
odoo/addons/stock_ownership_availability_rules/i18n/nl_NL.po
odoo/addons/stock_ownership_availability_rules/i18n/pt.po
odoo/addons/stock_ownership_availability_rules/i18n/stock_ownership_availability_rules.pot
odoo/addons/stock_ownership_availability_rules/model/__init__.py
odoo/addons/stock_ownership_availability_rules/model/product.py
odoo/addons/stock_ownership_availability_rules/model/quant.py
odoo/addons/stock_ownership_availability_rules/model/stock_inventory.py
odoo/addons/stock_ownership_availability_rules/security/group.xml
odoo/addons/stock_ownership_availability_rules/static/description/icon.png
odoo/addons/stock_ownership_availability_rules/tests/__init__.py
odoo/addons/stock_ownership_availability_rules/tests/test_default_quant_owner.py
odoo/addons/stock_ownership_availability_rules/tests/test_delivery_with_company_owner.py
odoo/addons/stock_ownership_availability_rules/tests/test_delivery_with_owner.py
odoo/addons/stock_ownership_availability_rules/tests/test_delivery_without_owner.py
odoo/addons/stock_ownership_availability_rules/tests/test_multicompany.py
odoo/addons/stock_ownership_availability_rules/view/move.xml
odoo/addons/stock_ownership_availability_rules/view/quant.xml
odoo10_addon_stock_ownership_availability_rules-10.0.1.0.2.dist-info/METADATA
odoo10_addon_stock_ownership_availability_rules-10.0.1.0.2.dist-info/RECORD
odoo10_addon_stock_ownership_availability_rules-10.0.1.0.2.dist-info/WHEEL
odoo10_addon_stock_ownership_availability_rules-10.0.1.0.2.dist-info/namespace_packages.txt
odoo10_addon_stock_ownership_availability_rules-10.0.1.0.2.dist-info/top_level.txt
